iqrfpy/ext/mqtt_transport/__init__.py
iqrfpy/ext/mqtt_transport/exceptions.py
iqrfpy/ext/mqtt_transport/mqtt_transport.py
iqrfpy/ext/mqtt_transport/objects.py
iqrfpy/ext/mqtt_transport/py.typed
iqrfpy_mqtt_transport-0.1.0.dist-info/LICENSE
iqrfpy_mqtt_transport-0.1.0.dist-info/METADATA
iqrfpy_mqtt_transport-0.1.0.dist-info/WHEEL
iqrfpy_mqtt_transport-0.1.0.dist-info/top_level.txt
iqrfpy_mqtt_transport-0.1.0.dist-info/RECORD
