Metadata-Version: 2.1
Name: iqrfpy-mqtt-transport
Version: 0.1.0
Summary: MQTT transport extension for iqrfpy
Home-page: https://gitlab.iqrf.org/open-source/iqrf-sdk/iqrfpy/iqrf-mqtt-transport
Author: Karel Hanák
Author-email: karel.hanak@iqrf.org
License: Apache-2.0
Project-URL: Homepage, https://gitlab.iqrf.org/open-source/iqrf-sdk/iqrfpy/iqrf-mqtt-transport
Project-URL: Changelog, https://gitlab.iqrf.org/open-source/iqrf-sdk/iqrfpy/iqrf-mqtt-transport/-/blob/master/changelog.md
Project-URL: Source code, https://gitlab.iqrf.org/open-source/iqrf-sdk/iqrfpy/iqrf-mqtt-transport
Project-URL: Issue tracker, https://gitlab.iqrf.org/open-source/iqrf-sdk/iqrfpy/iqrf-mqtt-transport/-/issues
Keywords: iqrf,mqtt
Classifier: Development Status :: 4 - Beta
Classifier: License :: OSI Approved :: Apache Software License
Classifier: Programming Language :: Python
Classifier: Programming Language :: Python :: 3
Classifier: Programming Language :: Python :: 3.10
Classifier: Programming Language :: Python :: 3.11
Classifier: Programming Language :: Python :: 3.12
Classifier: Operating System :: Microsoft :: Windows
Classifier: Operating System :: POSIX
Classifier: Operating System :: Unix
Classifier: Operating System :: MacOS
Requires-Python: >=3.10
License-File: LICENSE
Requires-Dist: iqrfpy >=0.2.0
Requires-Dist: paho-mqtt >=2.0.0
